audiobox/__init__.py
audiobox/audiobox.py
audiobox-0.0.6.dist-info/LICENSE
audiobox-0.0.6.dist-info/METADATA
audiobox-0.0.6.dist-info/WHEEL
audiobox-0.0.6.dist-info/top_level.txt
audiobox-0.0.6.dist-info/RECORD
