Metadata-Version: 2.2
Name: audiobox
Version: 0.0.6
Summary: AudioBox allows the user to play music and sound effects on any platform as long as you have the files.
Home-page: https://github.com/TaireruLLC/audiobox
Author: Taireru LLC
Author-email: tairerullc@gmail.com
License: MIT
Classifier: Programming Language :: Python :: 3
Classifier: License :: OSI Approved :: MIT License
Classifier: Operating System :: OS Independent
Requires-Python: >=3.6
License-File: LICENSE
Requires-Dist: requests
Requires-Dist: cryptography
Requires-Dist: altcolor>=0.0.3
Requires-Dist: mutagen
Requires-Dist: pygame
Dynamic: author
Dynamic: author-email
Dynamic: classifier
Dynamic: description
Dynamic: description-content-type
Dynamic: home-page
Dynamic: license
Dynamic: requires-dist
Dynamic: requires-python
Dynamic: summary
